{
  "version": "55-8_1ac4ee6",
  "branch": "gnome-nv",
  "deltas": [
    {
      "from_version": "55-8_803738e",
      "from_tag": "55-8_803738e",
      "filename": "skorionos-55-8_1ac4ee6-gnome-nv.from_55-8_803738e.skdelta",
      "checksum": "sha256:118fe8dcf934f57d54efaabf0d5ef17d0952eec2afd3fb7261228403b70814e3",
      "size": 210455736,
      "full_size": 2882015500,
      "target_meta_hash": "f54ee50cdbd07711ad5e1872feebf472bd347252b9f6962a659a7fb95ba720c6",
      "format": "rsync-batch"
    },
    {
      "from_version": "55-7_7aeb136",
      "from_tag": "55-7_7aeb136",
      "filename": "skorionos-55-8_1ac4ee6-gnome-nv.from_55-7_7aeb136.skdelta",
      "checksum": "sha256:f73904a6b126b7f0bbfec5b1ae586342b828704cef22ee00a9f56ec5472544a8",
      "size": 308947484,
      "full_size": 2882015500,
      "target_meta_hash": "f54ee50cdbd07711ad5e1872feebf472bd347252b9f6962a659a7fb95ba720c6",
      "format": "rsync-batch"
    },
    {
      "from_version": "55-5_0c87ab7",
      "from_tag": "55-5_0c87ab7",
      "filename": "skorionos-55-8_1ac4ee6-gnome-nv.from_55-5_0c87ab7.skdelta",
      "checksum": "sha256:3aa08390eed7267ac7fdd4481280d370605a6e082ea6c0c576732d382006b343",
      "size": 953401736,
      "full_size": 2882015500,
      "target_meta_hash": "f54ee50cdbd07711ad5e1872feebf472bd347252b9f6962a659a7fb95ba720c6",
      "format": "rsync-batch"
    },
    {
      "from_version": "55-8_5b6dbba",
      "from_tag": "55-8_5b6dbba",
      "filename": "skorionos-55-8_1ac4ee6-gnome-nv.from_55-8_5b6dbba.skdelta",
      "checksum": "sha256:b924ca25951c565a04d9aa9574b62e563381459098e3292c7aa8eec79f21a4a0",
      "size": 290430228,
      "full_size": 2882015500,
      "target_meta_hash": "f54ee50cdbd07711ad5e1872feebf472bd347252b9f6962a659a7fb95ba720c6",
      "format": "rsync-batch"
    },
    {
      "from_version": "55-6_3365803",
      "from_tag": "55-6_3365803",
      "filename": "skorionos-55-8_1ac4ee6-gnome-nv.from_55-6_3365803.skdelta",
      "checksum": "sha256:540ded1744c9739d6c9e7fd8a756b35bab2fcbaef28bd3be536e9e6e59117eef",
      "size": 322793436,
      "full_size": 2882015500,
      "target_meta_hash": "f54ee50cdbd07711ad5e1872feebf472bd347252b9f6962a659a7fb95ba720c6",
      "format": "rsync-batch"
    },
    {
      "from_version": "55-5_3e74b92",
      "from_tag": "55-5_3e74b92",
      "filename": "skorionos-55-8_1ac4ee6-gnome-nv.from_55-5_3e74b92.skdelta",
      "checksum": "sha256:5fe6c9ffe9ceabb77529bf1d90d4118c7ca3b9f9cd3e80c17ec19dac8d7b5f76",
      "size": 945222432,
      "full_size": 2882015500,
      "target_meta_hash": "f54ee50cdbd07711ad5e1872feebf472bd347252b9f6962a659a7fb95ba720c6",
      "format": "rsync-batch"
    },
    {
      "from_version": "55-8_1b73c16",
      "from_tag": "55-8_1b73c16",
      "filename": "skorionos-55-8_1ac4ee6-gnome-nv.from_55-8_1b73c16.skdelta",
      "checksum": "sha256:f514b5be544f77bd5d853fbd40451f11e2debe797cd5f78f828586538cba0dbd",
      "size": 223857136,
      "full_size": 2882015500,
      "target_meta_hash": "f54ee50cdbd07711ad5e1872feebf472bd347252b9f6962a659a7fb95ba720c6",
      "format": "rsync-batch"
    }
  ]
}
